<annotation>
	<folder>Chao_long</folder>
	<filename>Chao_long_469.jpg</filename>
	<path>C:\Users\ASUS\OneDrive\Máy tính\Emer\VNFoodDetection\images\Chao_long\Chao_long_469.jpg</path>
	<source>
		<database>Unknown</database>
	</source>
	<size>
		<width>640</width>
		<height>640</height>
		<depth>3</depth>
	</size>
	<segmented>0</segmented>
	<object>
		<name>Chao_long</name>
		<pose>Unspecified</pose>
		<truncated>0</truncated>
		<difficult>0</difficult>
		<bndbox>
			<xmin>32</xmin>
			<ymin>152</ymin>
			<xmax>590</xmax>
			<ymax>577</ymax>
		</bndbox>
	</object>
</annotation>
