<annotation verified="yes">
	<folder>Cao_lau</folder>
	<filename>Cao_lau_580.jpg</filename>
	<path>D:\hoc tap\chuyen nganh\emerging technologies\finall\VNFoodDetection\images\Cao_lau\Cao_lau_580.jpg</path>
	<source>
		<database>Unknown</database>
	</source>
	<size>
		<width>450</width>
		<height>338</height>
		<depth>3</depth>
	</size>
	<segmented>0</segmented>
	<object>
		<name>Cao_lau</name>
		<pose>Unspecified</pose>
		<truncated>0</truncated>
		<difficult>0</difficult>
		<bndbox>
			<xmin>69</xmin>
			<ymin>81</ymin>
			<xmax>302</xmax>
			<ymax>278</ymax>
		</bndbox>
	</object>
</annotation>
