<annotation>
	<folder>Banh_canh</folder>
	<filename>Banh_canh_280.jpg</filename>
	<path>D:\VNFoodDetection\images\Banh_canh\Banh_canh_280.jpg</path>
	<source>
		<database>Unknown</database>
	</source>
	<size>
		<width>820</width>
		<height>547</height>
		<depth>3</depth>
	</size>
	<segmented>0</segmented>
	<object>
		<name>Banh_canh</name>
		<pose>Unspecified</pose>
		<truncated>1</truncated>
		<difficult>0</difficult>
		<bndbox>
			<xmin>1</xmin>
			<ymin>17</ymin>
			<xmax>819</xmax>
			<ymax>545</ymax>
		</bndbox>
	</object>
</annotation>
