<annotation>
	<folder>Banh_canh</folder>
	<filename>Banh_canh_349.jpg</filename>
	<path>D:\VNFoodDetection\images\Banh_canh\Banh_canh_349.jpg</path>
	<source>
		<database>Unknown</database>
	</source>
	<size>
		<width>601</width>
		<height>361</height>
		<depth>3</depth>
	</size>
	<segmented>0</segmented>
	<object>
		<name>Banh_canh</name>
		<pose>Unspecified</pose>
		<truncated>1</truncated>
		<difficult>0</difficult>
		<bndbox>
			<xmin>1</xmin>
			<ymin>3</ymin>
			<xmax>600</xmax>
			<ymax>357</ymax>
		</bndbox>
	</object>
</annotation>
