<annotation verified="yes">
	<folder>Banh_bot_loc</folder>
	<filename>Banh_bot_loc_528.jpg</filename>
	<path>D:\Emerging Tech\Banh_bot_loc\Banh_bot_loc_528.jpg</path>
	<source>
		<database>Unknown</database>
	</source>
	<size>
		<width>397</width>
		<height>283</height>
		<depth>3</depth>
	</size>
	<segmented>0</segmented>
	<object>
		<name>Banh_bot_loc</name>
		<pose>Unspecified</pose>
		<truncated>0</truncated>
		<difficult>0</difficult>
		<bndbox>
			<xmin>46</xmin>
			<ymin>65</ymin>
			<xmax>223</xmax>
			<ymax>232</ymax>
		</bndbox>
	</object>
	<object>
		<name>Nuoc_mam</name>
		<pose>Unspecified</pose>
		<truncated>0</truncated>
		<difficult>0</difficult>
		<bndbox>
			<xmin>237</xmin>
			<ymin>107</ymin>
			<xmax>325</xmax>
			<ymax>199</ymax>
		</bndbox>
	</object>
</annotation>
