<annotation>
	<folder>Banh_bot_loc</folder>
	<filename>Banh_bot_loc_697.jpg</filename>
	<path>D:\Emerging Tech\Banh_bot_loc\Banh_bot_loc_697.jpg</path>
	<source>
		<database>Unknown</database>
	</source>
	<size>
		<width>1080</width>
		<height>1080</height>
		<depth>3</depth>
	</size>
	<segmented>0</segmented>
	<object>
		<name>Banh_bot_loc</name>
		<pose>Unspecified</pose>
		<truncated>0</truncated>
		<difficult>0</difficult>
		<bndbox>
			<xmin>72</xmin>
			<ymin>412</ymin>
			<xmax>657</xmax>
			<ymax>915</ymax>
		</bndbox>
	</object>
	<object>
		<name>Nuoc_mam</name>
		<pose>Unspecified</pose>
		<truncated>0</truncated>
		<difficult>0</difficult>
		<bndbox>
			<xmin>656</xmin>
			<ymin>352</ymin>
			<xmax>900</xmax>
			<ymax>513</ymax>
		</bndbox>
	</object>
</annotation>
