<annotation verified="yes">
	<folder>Banh_bot_loc</folder>
	<filename>Banh_bot_loc_588.jpg</filename>
	<path>D:\Emerging Tech\Banh_bot_loc\Banh_bot_loc_588.jpg</path>
	<source>
		<database>Unknown</database>
	</source>
	<size>
		<width>1080</width>
		<height>607</height>
		<depth>3</depth>
	</size>
	<segmented>0</segmented>
	<object>
		<name>Banh_bot_loc</name>
		<pose>Unspecified</pose>
		<truncated>0</truncated>
		<difficult>0</difficult>
		<bndbox>
			<xmin>439</xmin>
			<ymin>279</ymin>
			<xmax>721</xmax>
			<ymax>572</ymax>
		</bndbox>
	</object>
	<object>
		<name>Nuoc_tuong</name>
		<pose>Unspecified</pose>
		<truncated>0</truncated>
		<difficult>0</difficult>
		<bndbox>
			<xmin>450</xmin>
			<ymin>178</ymin>
			<xmax>550</xmax>
			<ymax>275</ymax>
		</bndbox>
	</object>
</annotation>
