<annotation>
	<folder>Banh_mi</folder>
	<filename>Banh_mi_1045.jpg</filename>
	<path>D:\Repos\VNFoodDetection\images\Banh_mi\Banh_mi_1045.jpg</path>
	<source>
		<database>Unknown</database>
	</source>
	<size>
		<width>1080</width>
		<height>1350</height>
		<depth>3</depth>
	</size>
	<segmented>0</segmented>
	<object>
		<name>Banh_mi</name>
		<pose>Unspecified</pose>
		<truncated>1</truncated>
		<difficult>0</difficult>
		<bndbox>
			<xmin>1</xmin>
			<ymin>611</ymin>
			<xmax>213</xmax>
			<ymax>1007</ymax>
		</bndbox>
	</object>
	<object>
		<name>Banh_mi</name>
		<pose>Unspecified</pose>
		<truncated>0</truncated>
		<difficult>0</difficult>
		<bndbox>
			<xmin>486</xmin>
			<ymin>411</ymin>
			<xmax>654</xmax>
			<ymax>676</ymax>
		</bndbox>
	</object>
	<object>
		<name>Thit</name>
		<pose>Unspecified</pose>
		<truncated>1</truncated>
		<difficult>0</difficult>
		<bndbox>
			<xmin>667</xmin>
			<ymin>137</ymin>
			<xmax>1080</xmax>
			<ymax>590</ymax>
		</bndbox>
	</object>
	<object>
		<name>Thit</name>
		<pose>Unspecified</pose>
		<truncated>1</truncated>
		<difficult>0</difficult>
		<bndbox>
			<xmin>713</xmin>
			<ymin>641</ymin>
			<xmax>1080</xmax>
			<ymax>1084</ymax>
		</bndbox>
	</object>
</annotation>
