<annotation>
	<folder>Banh_can</folder>
	<filename>Banh_can_338.jpg</filename>
	<path>D:\Emerging Tech\Banh_can\Banh_can_338.jpg</path>
	<source>
		<database>Unknown</database>
	</source>
	<size>
		<width>751</width>
		<height>532</height>
		<depth>3</depth>
	</size>
	<segmented>0</segmented>
	<object>
		<name>Banh_can</name>
		<pose>Unspecified</pose>
		<truncated>1</truncated>
		<difficult>0</difficult>
		<bndbox>
			<xmin>1</xmin>
			<ymin>58</ymin>
			<xmax>465</xmax>
			<ymax>477</ymax>
		</bndbox>
	</object>
	<object>
		<name>Nuoc_mam</name>
		<pose>Unspecified</pose>
		<truncated>1</truncated>
		<difficult>0</difficult>
		<bndbox>
			<xmin>465</xmin>
			<ymin>343</ymin>
			<xmax>682</xmax>
			<ymax>532</ymax>
		</bndbox>
	</object>
</annotation>
