<annotation>
	<folder>Banh_can</folder>
	<filename>Banh_can_27.jpg</filename>
	<path>D:\Emerging Tech\Banh_can\Banh_can_27.jpg</path>
	<source>
		<database>Unknown</database>
	</source>
	<size>
		<width>560</width>
		<height>420</height>
		<depth>3</depth>
	</size>
	<segmented>0</segmented>
	<object>
		<name>Banh_can</name>
		<pose>Unspecified</pose>
		<truncated>0</truncated>
		<difficult>0</difficult>
		<bndbox>
			<xmin>104</xmin>
			<ymin>110</ymin>
			<xmax>278</xmax>
			<ymax>220</ymax>
		</bndbox>
	</object>
	<object>
		<name>Banh_can</name>
		<pose>Unspecified</pose>
		<truncated>0</truncated>
		<difficult>0</difficult>
		<bndbox>
			<xmin>210</xmin>
			<ymin>214</ymin>
			<xmax>426</xmax>
			<ymax>383</ymax>
		</bndbox>
	</object>
</annotation>
