<annotation>
	<folder>Banh_can</folder>
	<filename>Banh_can_441.jpg</filename>
	<path>D:\Emerging Tech\Banh_can\Banh_can_441.jpg</path>
	<source>
		<database>Unknown</database>
	</source>
	<size>
		<width>1280</width>
		<height>720</height>
		<depth>3</depth>
	</size>
	<segmented>0</segmented>
	<object>
		<name>Banh_can</name>
		<pose>Unspecified</pose>
		<truncated>0</truncated>
		<difficult>0</difficult>
		<bndbox>
			<xmin>211</xmin>
			<ymin>186</ymin>
			<xmax>753</xmax>
			<ymax>680</ymax>
		</bndbox>
	</object>
	<object>
		<name>Banh_can</name>
		<pose>Unspecified</pose>
		<truncated>0</truncated>
		<difficult>0</difficult>
		<bndbox>
			<xmin>665</xmin>
			<ymin>24</ymin>
			<xmax>1167</xmax>
			<ymax>533</ymax>
		</bndbox>
	</object>
	<object>
		<name>Banh_can</name>
		<pose>Unspecified</pose>
		<truncated>1</truncated>
		<difficult>0</difficult>
		<bndbox>
			<xmin>1</xmin>
			<ymin>1</ymin>
			<xmax>459</xmax>
			<ymax>346</ymax>
		</bndbox>
	</object>
	<object>
		<name>Banh_can</name>
		<pose>Unspecified</pose>
		<truncated>1</truncated>
		<difficult>0</difficult>
		<bndbox>
			<xmin>614</xmin>
			<ymin>1</ymin>
			<xmax>1280</xmax>
			<ymax>150</ymax>
		</bndbox>
	</object>
</annotation>
