<annotation>
	<folder>Hu_tieu</folder>
	<filename>Hu_tieu_854.jpg</filename>
	<path>D:\N3CN22\CDCN\VNFoodDetection\images\Hu_tieu\Hu_tieu_854.jpg</path>
	<source>
		<database>Unknown</database>
	</source>
	<size>
		<width>1080</width>
		<height>1080</height>
		<depth>3</depth>
	</size>
	<segmented>0</segmented>
	<object>
		<name>Hu_tieu</name>
		<pose>Unspecified</pose>
		<truncated>0</truncated>
		<difficult>0</difficult>
		<bndbox>
			<xmin>10</xmin>
			<ymin>11</ymin>
			<xmax>1074</xmax>
			<ymax>1061</ymax>
		</bndbox>
	</object>
</annotation>
