<annotation>
	<folder>Banh_khot</folder>
	<filename>Banh_khot_529.jpg</filename>
	<path>D:\Repos\VNFoodDetection\images\Banh_khot\Banh_khot_529.jpg</path>
	<source>
		<database>Unknown</database>
	</source>
	<size>
		<width>960</width>
		<height>720</height>
		<depth>3</depth>
	</size>
	<segmented>0</segmented>
	<object>
		<name>Banh_khot</name>
		<pose>Unspecified</pose>
		<truncated>0</truncated>
		<difficult>0</difficult>
		<bndbox>
			<xmin>4</xmin>
			<ymin>7</ymin>
			<xmax>771</xmax>
			<ymax>687</ymax>
		</bndbox>
	</object>
	<object>
		<name>Nuoc_mam</name>
		<pose>Unspecified</pose>
		<truncated>1</truncated>
		<difficult>0</difficult>
		<bndbox>
			<xmin>744</xmin>
			<ymin>5</ymin>
			<xmax>960</xmax>
			<ymax>205</ymax>
		</bndbox>
	</object>
</annotation>
