<annotation>
	<folder>Goi_cuon</folder>
	<filename>Goi_cuon_424.jpg</filename>
	<path>D:\Repos\DemoHTML\VNFoodDetection\images\Goi_cuon\Goi_cuon_424.jpg</path>
	<source>
		<database>Unknown</database>
	</source>
	<size>
		<width>1280</width>
		<height>720</height>
		<depth>3</depth>
	</size>
	<segmented>0</segmented>
	<object>
		<name>Goi_cuon</name>
		<pose>Unspecified</pose>
		<truncated>0</truncated>
		<difficult>0</difficult>
		<bndbox>
			<xmin>6</xmin>
			<ymin>203</ymin>
			<xmax>127</xmax>
			<ymax>685</ymax>
		</bndbox>
	</object>
	<object>
		<name>Goi_cuon</name>
		<pose>Unspecified</pose>
		<truncated>0</truncated>
		<difficult>0</difficult>
		<bndbox>
			<xmin>89</xmin>
			<ymin>221</ymin>
			<xmax>353</xmax>
			<ymax>707</ymax>
		</bndbox>
	</object>
	<object>
		<name>Goi_cuon</name>
		<pose>Unspecified</pose>
		<truncated>0</truncated>
		<difficult>0</difficult>
		<bndbox>
			<xmin>340</xmin>
			<ymin>85</ymin>
			<xmax>521</xmax>
			<ymax>706</ymax>
		</bndbox>
	</object>
	<object>
		<name>Goi_cuon</name>
		<pose>Unspecified</pose>
		<truncated>0</truncated>
		<difficult>0</difficult>
		<bndbox>
			<xmin>488</xmin>
			<ymin>118</ymin>
			<xmax>648</xmax>
			<ymax>684</ymax>
		</bndbox>
	</object>
	<object>
		<name>Goi_cuon</name>
		<pose>Unspecified</pose>
		<truncated>0</truncated>
		<difficult>0</difficult>
		<bndbox>
			<xmin>608</xmin>
			<ymin>152</ymin>
			<xmax>779</xmax>
			<ymax>691</ymax>
		</bndbox>
	</object>
	<object>
		<name>Goi_cuon</name>
		<pose>Unspecified</pose>
		<truncated>0</truncated>
		<difficult>0</difficult>
		<bndbox>
			<xmin>759</xmin>
			<ymin>159</ymin>
			<xmax>934</xmax>
			<ymax>672</ymax>
		</bndbox>
	</object>
	<object>
		<name>Goi_cuon</name>
		<pose>Unspecified</pose>
		<truncated>0</truncated>
		<difficult>0</difficult>
		<bndbox>
			<xmin>876</xmin>
			<ymin>114</ymin>
			<xmax>1048</xmax>
			<ymax>672</ymax>
		</bndbox>
	</object>
	<object>
		<name>Goi_cuon</name>
		<pose>Unspecified</pose>
		<truncated>0</truncated>
		<difficult>0</difficult>
		<bndbox>
			<xmin>1027</xmin>
			<ymin>75</ymin>
			<xmax>1253</xmax>
			<ymax>706</ymax>
		</bndbox>
	</object>
</annotation>
