<annotation>
	<folder>Goi_cuon</folder>
	<filename>Goi_cuon_113.jpg</filename>
	<path>D:\Repos\DemoHTML\VNFoodDetection\images\Goi_cuon\Goi_cuon_113.jpg</path>
	<source>
		<database>Unknown</database>
	</source>
	<size>
		<width>1024</width>
		<height>766</height>
		<depth>3</depth>
	</size>
	<segmented>0</segmented>
	<object>
		<name>Mam_nem</name>
		<pose>Unspecified</pose>
		<truncated>0</truncated>
		<difficult>0</difficult>
		<bndbox>
			<xmin>418</xmin>
			<ymin>168</ymin>
			<xmax>874</xmax>
			<ymax>472</ymax>
		</bndbox>
	</object>
	<object>
		<name>Goi_cuon</name>
		<pose>Unspecified</pose>
		<truncated>0</truncated>
		<difficult>0</difficult>
		<bndbox>
			<xmin>319</xmin>
			<ymin>71</ymin>
			<xmax>470</xmax>
			<ymax>368</ymax>
		</bndbox>
	</object>
	<object>
		<name>Goi_cuon</name>
		<pose>Unspecified</pose>
		<truncated>0</truncated>
		<difficult>0</difficult>
		<bndbox>
			<xmin>86</xmin>
			<ymin>136</ymin>
			<xmax>369</xmax>
			<ymax>389</ymax>
		</bndbox>
	</object>
	<object>
		<name>Goi_cuon</name>
		<pose>Unspecified</pose>
		<truncated>0</truncated>
		<difficult>0</difficult>
		<bndbox>
			<xmin>64</xmin>
			<ymin>407</ymin>
			<xmax>499</xmax>
			<ymax>589</ymax>
		</bndbox>
	</object>
	<object>
		<name>Goi_cuon</name>
		<pose>Unspecified</pose>
		<truncated>0</truncated>
		<difficult>0</difficult>
		<bndbox>
			<xmin>220</xmin>
			<ymin>405</ymin>
			<xmax>505</xmax>
			<ymax>731</ymax>
		</bndbox>
	</object>
</annotation>
