<annotation>
	<folder>Banh_tet</folder>
	<filename>Banh_tet_132.jpg</filename>
	<path>D:\Repos\DemoHTML\VNFoodDetection\images\Banh_tet\Banh_tet_132.jpg</path>
	<source>
		<database>Unknown</database>
	</source>
	<size>
		<width>580</width>
		<height>304</height>
		<depth>3</depth>
	</size>
	<segmented>0</segmented>
	<object>
		<name>Banh_tet_nep_cam_dau_xanh</name>
		<pose>Unspecified</pose>
		<truncated>0</truncated>
		<difficult>0</difficult>
		<bndbox>
			<xmin>77</xmin>
			<ymin>13</ymin>
			<xmax>287</xmax>
			<ymax>88</ymax>
		</bndbox>
	</object>
	<object>
		<name>Banh_tet_nep_cam_dau_xanh</name>
		<pose>Unspecified</pose>
		<truncated>0</truncated>
		<difficult>0</difficult>
		<bndbox>
			<xmin>83</xmin>
			<ymin>66</ymin>
			<xmax>221</xmax>
			<ymax>242</ymax>
		</bndbox>
	</object>
	<object>
		<name>Do_chua</name>
		<pose>Unspecified</pose>
		<truncated>0</truncated>
		<difficult>0</difficult>
		<bndbox>
			<xmin>234</xmin>
			<ymin>85</ymin>
			<xmax>387</xmax>
			<ymax>259</ymax>
		</bndbox>
	</object>
</annotation>
