<annotation>
	<folder>Bun_dau_mam_tom</folder>
	<filename>Bun_dau_mam_tom_522.jpg</filename>
	<path>D:\VNFoodDetection\images\Bun_dau_mam_tom\Bun_dau_mam_tom_522.jpg</path>
	<source>
		<database>Unknown</database>
	</source>
	<size>
		<width>2698</width>
		<height>2227</height>
		<depth>3</depth>
	</size>
	<segmented>0</segmented>
	<object>
		<name>Bun_dau_mam_tom</name>
		<pose>Unspecified</pose>
		<truncated>1</truncated>
		<difficult>0</difficult>
		<bndbox>
			<xmin>376</xmin>
			<ymin>386</ymin>
			<xmax>2698</xmax>
			<ymax>1934</ymax>
		</bndbox>
	</object>
</annotation>
