<annotation>
	<folder>Bun_dau_mam_tom</folder>
	<filename>Bun_dau_mam_tom_301.jpg</filename>
	<path>D:\VNFoodDetection\images\Bun_dau_mam_tom\Bun_dau_mam_tom_301.jpg</path>
	<source>
		<database>Unknown</database>
	</source>
	<size>
		<width>576</width>
		<height>330</height>
		<depth>3</depth>
	</size>
	<segmented>0</segmented>
	<object>
		<name>Bun_dau_mam_tom</name>
		<pose>Unspecified</pose>
		<truncated>0</truncated>
		<difficult>0</difficult>
		<bndbox>
			<xmin>7</xmin>
			<ymin>77</ymin>
			<xmax>191</xmax>
			<ymax>280</ymax>
		</bndbox>
	</object>
	<object>
		<name>Bun_dau_mam_tom</name>
		<pose>Unspecified</pose>
		<truncated>0</truncated>
		<difficult>0</difficult>
		<bndbox>
			<xmin>198</xmin>
			<ymin>55</ymin>
			<xmax>364</xmax>
			<ymax>244</ymax>
		</bndbox>
	</object>
	<object>
		<name>Bun_dau_mam_tom</name>
		<pose>Unspecified</pose>
		<truncated>0</truncated>
		<difficult>0</difficult>
		<bndbox>
			<xmin>381</xmin>
			<ymin>51</ymin>
			<xmax>569</xmax>
			<ymax>235</ymax>
		</bndbox>
	</object>
</annotation>
